Subject/__init__.py
Subjectpy-0.1.0.dist-info/LICENSE
Subjectpy-0.1.0.dist-info/METADATA
Subjectpy-0.1.0.dist-info/WHEEL
Subjectpy-0.1.0.dist-info/top_level.txt
Subjectpy-0.1.0.dist-info/RECORD
