Metadata-Version: 2.1
Name: Subjectpy
Version: 0.1.0
Summary: Multi function application
Home-page: 
Author: Knowing
Author-email: Adam Garza <knowingadam@gmail.com>
License: MIT License        
Project-URL: Homepage, https://gitlab.com/projectstudios/subject
Project-URL: Bug Tracker, https://gitlab.com/projectstudios/subject/-/issues
Keywords: calculator
Classifier: Development Status :: 1 - Planning
Classifier: Intended Audience :: Developers
Classifier: Operating System :: Microsoft :: Windows :: Windows 10
Classifier: License :: OSI Approved :: MIT License
Classifier: Programming Language :: Python :: 3
Requires-Python: >=3.7
License-File: LICENSE
